python_explorer/__init__.py
python_explorer/assets/__init__.py
python_explorer/assets/bootstrap.min.css
python_explorer/assets/favicon.ico
python_explorer/cli/__init__.py
python_explorer/layouts/__init__.py
python_explorer/layouts/body_left.py
python_explorer/layouts/body_right_cyto.py
python_explorer/layouts/body_right_members.py
python_explorer/layouts/cyto_utils.py
python_explorer/layouts/header.py
python_explorer/layouts/layout_utils.py
python_explorer/layouts/main_page.py
python_explorer/layouts/stores.py
python_explorer/utils/__init__.py
python_explorer/utils/app.py
python_explorer/utils/callbacks.py
python_explorer/utils/envdata.py
python_explorer/utils/explore.py
python_explorer-0.1.0.dist-info/LICENSE
python_explorer-0.1.0.dist-info/METADATA
python_explorer-0.1.0.dist-info/WHEEL
python_explorer-0.1.0.dist-info/entry_points.txt
python_explorer-0.1.0.dist-info/top_level.txt
python_explorer-0.1.0.dist-info/RECORD
