Metadata-Version: 2.1
Name: python-explorer
Version: 0.1.0
Summary: A Python environment exploration interface
Home-page: https://github.com/nelsonseth/python-explorer
Author: Seth M. Nelson
Author-email: murrson@gmail.com
License: MIT
Classifier: License :: OSI Approved :: MIT License
Classifier: Programming Language :: Python :: 3
Requires-Python: >=3.10
License-File: LICENSE
Requires-Dist: dash >=2.11.1
Requires-Dist: dash-bootstrap-components >=1.4.1
Requires-Dist: dash-cytoscape >=0.3.0
Requires-Dist: dash-extensions >=1.0.3
Requires-Dist: dash-iconify >=0.1.2
Requires-Dist: dash-mantine-components >=0.12.1
Requires-Dist: pypandoc-binary >=1.11
Requires-Dist: waitress >=2.0.0
